http/__init__.py
http/event.py
http/http_methods.py
http/json_methods.py
http/mappings.py
http/util.py
sdk/__init__.py
sdk/exceptions.py
sdk/marshaller.py
sdk/types.py
cumason_cloudevents-1.0.1.dist-info/LICENSE
cumason_cloudevents-1.0.1.dist-info/METADATA
cumason_cloudevents-1.0.1.dist-info/WHEEL
cumason_cloudevents-1.0.1.dist-info/top_level.txt
cumason_cloudevents-1.0.1.dist-info/RECORD
