Metadata-Version: 2.1
Name: cumason-cloudevents
Version: 1.0.1
Summary: UNKNOWN
Home-page: UNKNOWN
Author: The Cloud Events Contributors
Author-email: cncfcloudevents@gmail.com
License: UNKNOWN
Platform: UNKNOWN
Classifier: Intended Audience :: Information Technology
Classifier: Intended Audience :: System Administrators
Classifier: License :: OSI Approved :: Apache Software License
Classifier: Operating System :: POSIX :: Linux
Classifier: Programming Language :: Python :: 3
Classifier: Programming Language :: Python :: 3.6
Classifier: Programming Language :: Python :: 3.7
Classifier: Programming Language :: Python :: 3.8
